logictools/__init__.py
logictools/expression_parser.py
logictools/legacy_questions.json
logictools/logic_rule_transforms.py
logictools/next_step.py
logictools/question_generator.py
logictools/questions.json
logictools/test_expressionparser.py
logictools/test_logicruletransforms.py
logictools/test_solutions.py
logictools/validation_exception.py
logictools/AI/__init__.py
logictools/AI/astar_heuristic_weights.txt
logictools/AI/astar_heuristics.py
logictools/AI/astar_search.py
logictools/AI/evaluate_astar_heuristic.py
logictools/AI/genetic_algorithm.py
logictools/AI/grammar.lark
logictools/AI/neural_heuristic/__init__.py
logictools/AI/neural_heuristic/dataset.py
logictools/AI/neural_heuristic/model.py
logictools/AI/neural_heuristic/neural_embedding_heuristic.py
logictools/AI/neural_heuristic/sample_train_model.py
logictools/AI/neural_heuristic/sim_net.py
logictools/AI/neural_heuristic/train.py
logictools/AI/neural_heuristic/training_data_generator.py
logiclearnertools-0.1.9.dist-info/AUTHORS.md
logiclearnertools-0.1.9.dist-info/LICENSE
logiclearnertools-0.1.9.dist-info/METADATA
logiclearnertools-0.1.9.dist-info/WHEEL
logiclearnertools-0.1.9.dist-info/top_level.txt
logiclearnertools-0.1.9.dist-info/RECORD
