Metadata-Version: 2.1
Name: logiclearnertools
Version: 0.1.9
Summary: Logic Learner library
Home-page: https://github.com/ccnmtl/logiclearnertools
Author: Natalia Dittren, Columbia University Computer Science Faculty and Students
Author-email: natalia.d@columbia.edu
License: GPLv3+
Platform: any
License-File: LICENSE
License-File: AUTHORS.md
